moex_store/__init__.py
moex_store/dns_client.py
moex_store/futures.py
moex_store/patch_aiohttp.py
moex_store/store.py
moex_store/tf.py
moex_store-0.2.139.dist-info/METADATA
moex_store-0.2.139.dist-info/WHEEL
moex_store-0.2.139.dist-info/top_level.txt
moex_store-0.2.139.dist-info/RECORD
