Metadata-Version: 2.4
Name: moex_store
Version: 0.2.139
Summary: MOEX Store for Backtrader
Author-email: Celeevo <admin@backtrader.ru>
Project-URL: Homepage, https://github.com/Celeevo/moex_store
Project-URL: Issues, https://github.com/Celeevo/moex_store/issues
Keywords: backtrader,moex,backtesting,datafeed,store,cerebro
Classifier: Programming Language :: Python :: 3
Classifier: Operating System :: OS Independent
Classifier: License :: OSI Approved :: MIT License
Requires-Python: >=3.9
Requires-Dist: aiodns>=3.2.0
Requires-Dist: aiohttp>=3.9.5
Requires-Dist: aiomoex<2.1.0,>=2.0.0
Requires-Dist: aioresponses>=0.7.6
Requires-Dist: aiosignal>=1.3.1
Requires-Dist: attrs>=23.2.0
Requires-Dist: backtrader>=1.9.78.123
Requires-Dist: cffi>=1.16.0
Requires-Dist: colorama>=0.4.6
Requires-Dist: contourpy>=1.2.1
Requires-Dist: cycler>=0.12.1
Requires-Dist: fonttools>=4.53.1
Requires-Dist: frozenlist>=1.4.1
Requires-Dist: idna>=3.7
Requires-Dist: kiwisolver>=1.4.5
Requires-Dist: matplotlib>=3.8.4
Requires-Dist: multidict>=6.0.5
Requires-Dist: numpy>=2.0.1
Requires-Dist: packaging>=24.1
Requires-Dist: pandas>=2.2.2
Requires-Dist: pillow>=10.4.0
Requires-Dist: pycares>=4.4.0
Requires-Dist: pycparser>=2.22
Requires-Dist: pyparsing>=3.1.2
Requires-Dist: python-dateutil>=2.9.0.post0
Requires-Dist: pytz>=2024.1
Requires-Dist: six>=1.16.0
Requires-Dist: tqdm>=4.66.4
Requires-Dist: tzdata>=2024.1
Requires-Dist: yarl>=1.9.4
